Workbook
Name Slicer_Category: #N/A
Name Slicer_Category2: #N/A

Sheet dashboard

Sheet forecast_model_validation
B3: Forecast Model Validation
B4: Basics
A5: Date | B5: forecast_LR | C5: forecast_seasonal_index | D5: acutal_22/23
A6: 44562 | D6: 2100
A7: 44593 | D7: 2050
A8: 44621 | D8: 2200
A9: 44652 | D9: 2100
A10: 44682 | D10: 2000
A11: 44713 | D11: 1200
A12: 44743 | D12: 2100
A13: 44774 | D13: 2150
A14: 44805 | D14: 1900
A15: 44835 | D15: 2050
A16: 44866 | D16: 2100
A17: 44896 | D17: 2150
... A29: 45261 | D29: 2900
A30: 45292 | B30: 2938.0356 | C30: 2666.2816
A31: 45323 | B31: 3126.5481 | C31: 2690.558
A32: 45352 | B32: 3515.2484 | C32: 2968.766
A33: 45383 | B33: 3554.0399 | C33: 2871.0534
A34: 45413 | B34: 3492.7996 | C34: 2714.8345
A35: 45444 | B35: 2652.1769 | C35: 1523.5895
A36: 45474 | B36: 3783.7798 | C36: 2841.8002
A37: 45505 | B37: 3993.4307 | C37: 2993.0425
A38: 45536 | B38: 3831.2115 | C38: 2675.628
A39: 45566 | B39: 4070.0418 | C39: 2866.0767
A40: 45597 | B40: 4282.8361 | C40: 3017.3189
A41: 45627 | B41: 4305.3844 | C41: 3168.5611

Sheet inventory
A1: Date | B1: Category | C1: Lead Time | D1: Start Inv | E1: Production Plan | F1: End Inv | G1: Forecast_index | H1: Target Buffer | I1: Status
A2: 45292 | B2: Electronics | C2: 14 | D2: =data!H25 -> 3450 | E2: =MAX(0,H2+G2-D2) -> 0 | F2: =D2+E2-G2 -> 2141.7561 | G2: =forecast!M74 -> 1308.2439 | H2: =G2*$M$7 -> 1569.8927 | I2: =IF(F2<0, "STOCKOUT", IF(F2<(G2*0.5), "LOW STOCK", IF(F2>(G2*3), "OVERSTOCK", "HEALTHY"))) -> HEALTHY | M2: Service Level
A3: 45323 | B3: Electronics | C3: 14 | D3: =F2 -> 2141.7561 | E3: =MAX(0,H3+G3-D3) -> 745.1639 | F3: =D3+E3-G3 -> 1574.6836 | G3: =forecast!M75 -> 1312.2363 | H3: =G3*$M$7 -> 1574.6836 | I3: =IF(F3<0, "STOCKOUT", IF(F3<(G3*0.5), "LOW STOCK", IF(F3>(G3*3), "OVERSTOCK", "HEALTHY"))) -> HEALTHY | M3: 0.95
A4: 45352 | B4: Electronics | C4: 15 | D4: =F3 -> 1574.6836 | E4: =MAX(0,H4+G4-D4) -> 1739.0262 | F4: =D4+E4-G4 -> 1807.4781 | G4: =forecast!M76 -> 1506.2317 | H4: =G4*$M$7 -> 1807.4781 | I4: =IF(F4<0, "STOCKOUT", IF(F4<(G4*0.5), "LOW STOCK", IF(F4>(G4*3), "OVERSTOCK", "HEALTHY"))) -> HEALTHY
A5: 45383 | B5: Electronics | C5: 14 | D5: =F4 -> 1807.4781 | E5: =MAX(0,H5+G5-D5) -> 1937.4133 | F5: =D5+E5-G5 -> 2042.668 | G5: =forecast!M77 -> 1702.2233 | H5: =G5*$M$7 -> 2042.668 | I5: =IF(F5<0, "STOCKOUT", IF(F5<(G5*0.5), "LOW STOCK", IF(F5>(G5*3), "OVERSTOCK", "HEALTHY"))) -> HEALTHY | M5: Safety Stock
A6: 45413 | B6: Electronics | C6: 16 | D6: =F5 -> 2042.668 | E6: =MAX(0,H6+G6-D6) -> 2496.7152 | F6: =D6+E6-G6 -> 2476.0272 | G6: =forecast!M78 -> 2063.356 | H6: =G6*$M$7 -> 2476.0272 | I6: =IF(F6<0, "STOCKOUT", IF(F6<(G6*0.5), "LOW STOCK", IF(F6>(G6*3), "OVERSTOCK", "HEALTHY"))) -> HEALTHY | M6: Electronics | N6: Basics | O6: Office
A7: 45444 | B7: Electronics | C7: 14 | D7: =F6 -> 2476.0272 | E7: =MAX(0,H7+G7-D7) -> 2172.7484 | F7: =D7+E7-G7 -> 2535.6958 | G7: =forecast!M79 -> 2113.0798 | H7: =G7*$M$7 -> 2535.6958 | I7: =IF(F7<0, "STOCKOUT", IF(F7<(G7*0.5), "LOW STOCK", IF(F7>(G7*3), "OVERSTOCK", "HEALTHY"))) -> HEALTHY | M7: 1.2 | N7: 0.5 | O7: 1
A8: 45474 | B8: Electronics | C8: 18 | D8: =F7 -> 2535.6958 | E8: =MAX(0,H8+G8-D8) -> 2058.3836 | F8: =D8+E8-G8 -> 2505.8615 | G8: =forecast!M80 -> 2088.2179 | H8: =G8*$M$7 -> 2505.8615 | I8: =IF(F8<0, "STOCKOUT", IF(F8<(G8*0.5), "LOW STOCK", IF(F8>(G8*3), "OVERSTOCK", "HEALTHY"))) -> HEALTHY
A9: 45505 | B9: Electronics | C9: 14 | D9: =F8 -> 2505.8615 | E9: =MAX(0,H9+G9-D9) -> 1044.1997 | F9: =D9+E9-G9 -> 1936.397 | G9: =forecast!M81 -> 1613.6642 | H9: =G9*$M$7 -> 1936.397 | I9: =IF(F9<0, "STOCKOUT", IF(F9<(G9*0.5), "LOW STOCK", IF(F9>(G9*3), "OVERSTOCK", "HEALTHY"))) -> HEALTHY
A10: 45536 | B10: Electronics | C10: 14 | D10: =F9 -> 1936.397 | E10: =MAX(0,H10+G10-D10) -> 1613.6642 | F10: =D10+E10-G10 -> 1936.397 | G10: =forecast!M82 -> 1613.6642 | H10: =G10*$M$7 -> 1936.397 | I10: =IF(F10<0, "STOCKOUT", IF(F10<(G10*0.5), "LOW STOCK", IF(F10>(G10*3), "OVERSTOCK", "HEALTHY"))) -> HEALTHY
A11: 45566 | B11: Electronics | C11: 15 | D11: =F10 -> 1936.397 | E11: =MAX(0,H11+G11-D11) -> 3375.5198 | F11: =D11+E11-G11 -> 2897.4091 | G11: =forecast!M83 -> 2414.5076 | H11: =G11*$M$7 -> 2897.4091 | I11: =IF(F11<0, "STOCKOUT", IF(F11<(G11*0.5), "LOW STOCK", IF(F11>(G11*3), "OVERSTOCK", "HEALTHY"))) -> HEALTHY
A12: 45597 | B12: Electronics | C12: 22 | D12: =F11 -> 2897.4091 | E12: =MAX(0,H12+G12-D12) -> 5528.9956 | F12: =D12+E12-G12 -> 4596.2208 | G12: =forecast!M84 -> 3830.184 | H12: =G12*$M$7 -> 4596.2208 | I12: =IF(F12<0, "STOCKOUT", IF(F12<(G12*0.5), "LOW STOCK", IF(F12>(G12*3), "OVERSTOCK", "HEALTHY"))) -> HEALTHY
A13: 45627 | B13: Electronics | C13: 25 | D13: =F12 -> 4596.2208 | E13: =MAX(0,H13+G13-D13) -> 4329.2367 | F13: =D13+E13-G13 -> 4868.4313 | G13: =forecast!M85 -> 4057.0261 | H13: =G13*$M$7 -> 4868.4313 | I13: =IF(F13<0, "STOCKOUT", IF(F13<(G13*0.5), "LOW STOCK", IF(F13>(G13*3), "OVERSTOCK", "HEALTHY"))) -> HEALTHY
A14: 45292 | B14: Basics | C14: 7 | D14: =data!H49 -> 1450 | E14: =MAX(0,H14+G14-D14) -> 2549.4224 | F14: =D14+E14-G14 -> 1333.1408 | G14: =forecast!M86 -> 2666.2816 | H14: =G14*$N$7 -> 1333.1408 | I14: =IF(F14<0, "STOCKOUT", IF(F14<(G14*0.5), "LOW STOCK", IF(F14>(G14*3), "OVERSTOCK", "HEALTHY"))) -> HEALTHY
A15: 45323 | B15: Basics | C15: 7 | D15: =F14 -> 1333.1408 | E15: =MAX(0,H15+G15-D15) -> 2702.6962 | F15: =D15+E15-G15 -> 1345.279 | G15: =forecast!M87 -> 2690.558 | H15: =G15*$N$7 -> 1345.279 | I15: =IF(F15<0, "STOCKOUT", IF(F15<(G15*0.5), "LOW STOCK", IF(F15>(G15*3), "OVERSTOCK", "HEALTHY"))) -> HEALTHY
A16: 45352 | B16: Basics | C16: 8 | D16: =F15 -> 1345.279 | E16: =MAX(0,H16+G16-D16) -> 3107.87 | F16: =D16+E16-G16 -> 1484.383 | G16: =forecast!M88 -> 2968.766 | H16: =G16*$N$7 -> 1484.383 | I16: =IF(F16<0, "STOCKOUT", IF(F16<(G16*0.5), "LOW STOCK", IF(F16>(G16*3), "OVERSTOCK", "HEALTHY"))) -> HEALTHY
A17: 45383 | B17: Basics | C17: 7 | D17: =F16 -> 1484.383 | E17: =MAX(0,H17+G17-D17) -> 2822.197 | F17: =D17+E17-G17 -> 1435.5267 | G17: =forecast!M89 -> 2871.0534 | H17: =G17*$N$7 -> 1435.5267 | I17: =IF(F17<0, "STOCKOUT", IF(F17<(G17*0.5), "LOW STOCK", IF(F17>(G17*3), "OVERSTOCK", "HEALTHY"))) -> HEALTHY
A18: 45413 | B18: Basics | C18: 7 | D18: =F17 -> 1435.5267 | E18: =MAX(0,H18+G18-D18) -> 2636.725 | F18: =D18+E18-G18 -> 1357.4172 | G18: =forecast!M90 -> 2714.8345 | H18: =G18*$N$7 -> 1357.4172 | I18: =IF(F18<0, "STOCKOUT", IF(F18<(G18*0.5), "LOW STOCK", IF(F18>(G18*3), "OVERSTOCK", "HEALTHY"))) -> HEALTHY
A19: 45444 | B19: Basics | C19: 25 | D19: =F18 -> 1357.4172 | E19: =MAX(0,H19+G19-D19) -> 927.96698 | F19: =D19+E19-G19 -> 761.79473 | G19: =forecast!M91 -> 1523.5895 | H19: =G19*$N$7 -> 761.79473 | I19: =IF(F19<0, "STOCKOUT", IF(F19<(G19*0.5), "LOW STOCK", IF(F19>(G19*3), "OVERSTOCK", "HEALTHY"))) -> HEALTHY
A20: 45474 | B20: Basics | C20: 7 | D20: =F19 -> 761.79473 | E20: =MAX(0,H20+G20-D20) -> 3500.9056 | F20: =D20+E20-G20 -> 1420.9001 | G20: =forecast!M92 -> 2841.8002 | H20: =G20*$N$7 -> 1420.9001 | I20: =IF(F20<0, "STOCKOUT", IF(F20<(G20*0.5), "LOW STOCK", IF(F20>(G20*3), "OVERSTOCK", "HEALTHY"))) -> HEALTHY
A21: 45505 | B21: Basics | C21: 7 | D21: =F20 -> 1420.9001 | E21: =MAX(0,H21+G21-D21) -> 3068.6636 | F21: =D21+E21-G21 -> 1496.5212 | G21: =forecast!M93 -> 2993.0425 | H21: =G21*$N$7 -> 1496.5212 | I21: =IF(F21<0, "STOCKOUT", IF(F21<(G21*0.5), "LOW STOCK", IF(F21>(G21*3), "OVERSTOCK", "HEALTHY"))) -> HEALTHY
A22: 45536 | B22: Basics | C22: 7 | D22: =F21 -> 1496.5212 | E22: =MAX(0,H22+G22-D22) -> 2516.9208 | F22: =D22+E22-G22 -> 1337.814 | G22: =forecast!M94 -> 2675.628 | H22: =G22*$N$7 -> 1337.814 | I22: =IF(F22<0, "STOCKOUT", IF(F22<(G22*0.5), "LOW STOCK", IF(F22>(G22*3), "OVERSTOCK", "HEALTHY"))) -> HEALTHY
A23: 45566 | B23: Basics | C23: 7 | D23: =F22 -> 1337.814 | E23: =MAX(0,H23+G23-D23) -> 2961.301 | F23: =D23+E23-G23 -> 1433.0383 | G23: =forecast!M95 -> 2866.0767 | H23: =G23*$N$7 -> 1433.0383 | I23: =IF(F23<0, "STOCKOUT", IF(F23<(G23*0.5), "LOW STOCK", IF(F23>(G23*3), "OVERSTOCK", "HEALTHY"))) -> HEALTHY
A24: 45597 | B24: Basics | C24: 7 | D24: =F23 -> 1433.0383 | E24: =MAX(0,H24+G24-D24) -> 3092.94 | F24: =D24+E24-G24 -> 1508.6595 | G24: =forecast!M96 -> 3017.3189 | H24: =G24*$N$7 -> 1508.6595 | I24: =IF(F24<0, "STOCKOUT", IF(F24<(G24*0.5), "LOW STOCK", IF(F24>(G24*3), "OVERSTOCK", "HEALTHY"))) -> HEALTHY
A25: 45627 | B25: Basics | C25: 7 | D25: =F24 -> 1508.6595 | E25: =MAX(0,H25+G25-D25) -> 3244.1823 | F25: =D25+E25-G25 -> 1584.2806 | G25: =forecast!M97 -> 3168.5611 | H25: =G25*$N$7 -> 1584.2806 | I25: =IF(F25<0, "STOCKOUT", IF(F25<(G25*0.5), "LOW STOCK", IF(F25>(G25*3), "OVERSTOCK", "HEALTHY"))) -> HEALTHY
A26: 45292 | B26: Office | C26: 30 | D26: =data!H73 -> 900 | E26: =MAX(0,H26+G26-D26) -> 715.96939 | F26: =D26+E26-G26 -> 807.98469 | G26: =forecast!M98 -> 807.98469 | H26: =G26*$O$7 -> 807.98469 | I26: =IF(F26<0, "STOCKOUT", IF(F26<(G26*0.5), "LOW STOCK", IF(F26>(G26*3), "OVERSTOCK", "HEALTHY"))) -> HEALTHY
A27: 45323 | B27: Office | C27: 30 | D27: =F26 -> 807.98469 | E27: =MAX(0,H27+G27-D27) -> 954.36224 | F27: =D27+E27-G27 -> 881.17347 | G27: =forecast!M99 -> 881.17347 | H27: =G27*$O$7 -> 881.17347 | I27: =IF(F27<0, "STOCKOUT", IF(F27<(G27*0.5), "LOW STOCK", IF(F27>(G27*3), "OVERSTOCK", "HEALTHY"))) -> HEALTHY
A28: 45352 | B28: Office | C28: 30 | D28: =F27 -> 881.17347 | E28: =MAX(0,H28+G28-D28) -> 946.12245 | F28: =D28+E28-G28 -> 913.64796 | G28: =forecast!M100 -> 913.64796 | H28: =G28*$O$7 -> 913.64796 | I28: =IF(F28<0, "STOCKOUT", IF(F28<(G28*0.5), "LOW STOCK", IF(F28>(G28*3), "OVERSTOCK", "HEALTHY"))) -> HEALTHY
A29: 45383 | B29: Office | C29: 30 | D29: =F28 -> 913.64796 | E29: =MAX(0,H29+G29-D29) -> 2280.4847 | F29: =D29+E29-G29 -> 1597.0663 | G29: =forecast!M101 -> 1597.0663 | H29: =G29*$O$7 -> 1597.0663 | I29: =IF(F29<0, "STOCKOUT", IF(F29<(G29*0.5), "LOW STOCK", IF(F29>(G29*3), "OVERSTOCK", "HEALTHY"))) -> HEALTHY
A30: 45413 | B30: Office | C30: 30 | D30: =F29 -> 1597.0663 | E30: =MAX(0,H30+G30-D30) -> 525.89286 | F30: =D30+E30-G30 -> 1061.4796 | G30: =forecast!M102 -> 1061.4796 | H30: =G30*$O$7 -> 1061.4796 | I30: =IF(F30<0, "STOCKOUT", IF(F30<(G30*0.5), "LOW STOCK", IF(F30>(G30*3), "OVERSTOCK", "HEALTHY"))) -> HEALTHY
A31: 45444 | B31: Office | C31: 30 | D31: =F30 -> 1061.4796 | E31: =MAX(0,H31+G31-D31) -> 833.67347 | F31: =D31+E31-G31 -> 947.57653 | G31: =forecast!M103 -> 947.57653 | H31: =G31*$O$7 -> 947.57653 | I31: =IF(F31<0, "STOCKOUT", IF(F31<(G31*0.5), "LOW STOCK", IF(F31>(G31*3), "OVERSTOCK", "HEALTHY"))) -> HEALTHY
A32: 45474 | B32: Office | C32: 30 | D32: =F31 -> 947.57653 | E32: =MAX(0,H32+G32-D32) -> 1243.2398 | F32: =D32+E32-G32 -> 1095.4082 | G32: =forecast!M104 -> 1095.4082 | H32: =G32*$O$7 -> 1095.4082 | I32: =IF(F32<0, "STOCKOUT", IF(F32<(G32*0.5), "LOW STOCK", IF(F32>(G32*3), "OVERSTOCK", "HEALTHY"))) -> HEALTHY
A33: 45505 | B33: Office | C33: 30 | D33: =F32 -> 1095.4082 | E33: =MAX(0,H33+G33-D33) -> 2505.8673 | F33: =D33+E33-G33 -> 1800.6378 | G33: =forecast!M105 -> 1800.6378 | H33: =G33*$O$7 -> 1800.6378 | I33: =IF(F33<0, "STOCKOUT", IF(F33<(G33*0.5), "LOW STOCK", IF(F33>(G33*3), "OVERSTOCK", "HEALTHY"))) -> HEALTHY
A34: 45536 | B34: Office | C34: 30 | D34: =F33 -> 1800.6378 | E34: =MAX(0,H34+G34-D34) -> 70.280612 | F34: =D34+E34-G34 -> 935.45918 | G34: =forecast!M106 -> 935.45918 | H34: =G34*$O$7 -> 935.45918 | I34: =IF(F34<0, "STOCKOUT", IF(F34<(G34*0.5), "LOW STOCK", IF(F34>(G34*3), "OVERSTOCK", "HEALTHY"))) -> HEALTHY
A35: 45566 | B35: Office | C35: 30 | D35: =F34 -> 935.45918 | E35: =MAX(0,H35+G35-D35) -> 2670.6633 | F35: =D35+E35-G35 -> 1803.0612 | G35: =forecast!M107 -> 1803.0612 | H35: =G35*$O$7 -> 1803.0612 | I35: =IF(F35<0, "STOCKOUT", IF(F35<(G35*0.5), "LOW STOCK", IF(F35>(G35*3), "OVERSTOCK", "HEALTHY"))) -> HEALTHY
A36: 45597 | B36: Office | C36: 30 | D36: =F35 -> 1803.0612 | E36: =MAX(0,H36+G36-D36) -> 455.61224 | F36: =D36+E36-G36 -> 1129.3367 | G36: =forecast!M108 -> 1129.3367 | H36: =G36*$O$7 -> 1129.3367 | I36: =IF(F36<0, "STOCKOUT", IF(F36<(G36*0.5), "LOW STOCK", IF(F36>(G36*3), "OVERSTOCK", "HEALTHY"))) -> HEALTHY
A37: 45627 | B37: Office | C37: 30 | D37: =F36 -> 1129.3367 | E37: =MAX(0,H37+G37-D37) -> 1289.2857 | F37: =D37+E37-G37 -> 1209.3112 | G37: =forecast!M109 -> 1209.3112 | H37: =G37*$O$7 -> 1209.3112 | I37: =IF(F37<0, "STOCKOUT", IF(F37<(G37*0.5), "LOW STOCK", IF(F37>(G37*3), "OVERSTOCK", "HEALTHY"))) -> HEALTHY

Sheet stress_test
A3: Date | B3: Sum of High Demand | C3: Sum of Forecast_index | D3: Sum of Low Demand | E3: Sum of The Gap
A4: 45292 | B4: 4201.7476 | C4: 2666.2816 | D4: 1130.8156 | E4: 3070.932
A5: 45323 | B5: 4240.0044 | C5: 2690.558 | D5: 1141.1116 | E5: 3098.8928
A6: 45352 | B6: 4678.4277 | C6: 2968.766 | D6: 1259.1044 | E6: 3419.3232
A7: 45383 | B7: 4524.4439 | C7: 2871.0534 | D7: 1217.6628 | E7: 3306.7811
A8: 45413 | B8: 4278.2612 | C8: 2714.8345 | D8: 1151.4077 | E8: 3126.8535
A9: 45444 | B9: 2400.9986 | C9: 1523.5895 | D9: 646.18033 | E9: 1754.8183
A10: 45474 | B10: 4478.3444 | C10: 2841.8002 | D10: 1205.256 | E10: 3273.0884
A11: 45505 | B11: 4716.6845 | C11: 2993.0425 | D11: 1269.4005 | E11: 3447.284
A12: 45536 | B12: 4216.4764 | C12: 2675.628 | D12: 1134.7796 | E12: 3081.6969
A13: 45566 | B13: 4516.6013 | C13: 2866.0767 | D13: 1215.5521 | E13: 3301.0492
A14: 45597 | B14: 4754.9413 | C14: 3017.3189 | D14: 1279.6965 | E14: 3475.2448
A15: 45627 | B15: 4993.2814 | C15: 3168.5611 | D15: 1343.8409 | E15: 3649.4404
A16: Grand Total | B16: 52000.213 | C16: 32997.51 | D16: 13994.808 | E16: 38005.405

Sheet forecast
A1: Date | B1: Category | C1: Forecast | D1: Actual | E1: Lead Time | F1: Start Inv | G1: Planned Prod | H1: End Inv | I1: Logic/Driver | J1: Forecast_2024 | K1: Index by Year | L1: Seasonal Index | M1: Forecast_index | N1: Volatility | O1: High Demand | P1: Low Demand | Q1: The Gap | T1: Electronics | U1: Basics | V1: Office
A2: 44562 | B2: Electronics | C2: 1200 | D2: 1150 | E2: 14 | F2: 2000 | G2: 1250 | H2: 2100 | I2: Policy-based | K2: =D2/AVERAGEIFS($D$2:$D$73,$B$2:$B$73,B2,$A$2:$A$73,"<2023-1-1") -> 0.62162162 | N2: =(D2-C2)/C2 -> -0.041666667 | S2: Total Sales 2022 | T2: =SUMIFS($D$2:$D$73, $B$2:$B$73, "Electronics",$A$2:$A$73, "<2023-01-01") -> 22200 | U2: =SUMIFS($D$2:$D$73, $B$2:$B$73, "Basics",$A$2:$A$73, "<2023-01-01") -> 24100 | V2: =SUMIFS($D$2:$D$73, $B$2:$B$73, "Office",$A$2:$A$73, "<2023-01-01") -> 7700
A3: 44593 | B3: Electronics | C3: 1150 | D3: 1250 | E3: 14 | F3: 2100 | G3: 1200 | H3: 2050 | I3: Policy-based | K3: =D3/AVERAGEIFS($D$2:$D$73,$B$2:$B$73,B3,$A$2:$A$73,"<2023-1-1") -> 0.67567568 | N3: =(D3-C3)/C3 -> 0.086956522 | S3: Total Sales 2023 | T3: =SUMIFS($D$2:$D$73, $B$2:$B$73, "Electronics",$A$2:$A$73, ">=2023-01-01") -> 23850 | U3: =SUMIFS($D$2:$D$73, $B$2:$B$73, "Basics",$A$2:$A$73, ">=2023-01-01") -> 28200 | V3: =SUMIFS($D$2:$D$73, $B$2:$B$73, "Office",$A$2:$A$73, ">=2023-01-01") -> 10450
A4: 44621 | B4: Electronics | C4: 1300 | D4: 1400 | E4: 15 | F4: 2050 | G4: 1350 | H4: 2000 | I4: Buffer Build | K4: =D4/AVERAGEIFS($D$2:$D$73,$B$2:$B$73,B4,$A$2:$A$73,"<2023-1-1") -> 0.75675676 | N4: =(D4-C4)/C4 -> 0.076923077 | S4: Growth Rate | T4: =(T3-T2)/T2 -> 0.074324324 | U4: =(U3-U2)/U2 -> 0.17012448 | V4: =(V3-V2)/V2 -> 0.35714286
A5: 44652 | B5: Electronics | C5: 1250 | D5: 1600 | E5: 14 | F5: 2000 | G5: 1300 | H5: 1700 | I5: Supply Lag | K5: =D5/AVERAGEIFS($D$2:$D$73,$B$2:$B$73,B5,$A$2:$A$73,"<2023-1-1") -> 0.86486486 | N5: =(D5-C5)/C5 -> 0.28
A6: 44682 | B6: Electronics | C6: 1400 | D6: 1900 | E6: 16 | F6: 1700 | G6: 1450 | H6: 1250 | I6: High Sales | K6: =D6/AVERAGEIFS($D$2:$D$73,$B$2:$B$73,B6,$A$2:$A$73,"<2023-1-1") -> 1.027027 | N6: =(D6-C6)/C6 -> 0.35714286 | S6: Sigma | T6: =_xlfn.STDEV.P(N2:N73) -> 0.29381781
A7: 44713 | B7: Electronics | C7: 1600 | D7: 1800 | E7: 14 | F7: 1250 | G7: 2100 | H7: 1550 | I7: Recovery | K7: =D7/AVERAGEIFS($D$2:$D$73,$B$2:$B$73,B7,$A$2:$A$73,"<2023-1-1") -> 0.97297297 | N7: =(D7-C7)/C7 -> 0.125 | S7: 95% confidence level | T7: 1.96
A8: 44743 | B8: Electronics | C8: 1900 | D8: 1850 | E8: 18 | F8: 1550 | G8: 1950 | H8: 1650 | I8: Refilling | K8: =D8/AVERAGEIFS($D$2:$D$73,$B$2:$B$73,B8,$A$2:$A$73,"<2023-1-1") -> 1 | N8: =(D8-C8)/C8 -> -0.026315789
A9: 44774 | B9: Electronics | C9: 1500 | D9: 1400 | E9: 14 | F9: 1650 | G9: 1550 | H9: 1800 | I9: Stabilizing | K9: =D9/AVERAGEIFS($D$2:$D$73,$B$2:$B$73,B9,$A$2:$A$73,"<2023-1-1") -> 0.75675676 | N9: =(D9-C9)/C9 -> -0.066666667
A10: 44805 | B10: Electronics | C10: 1450 | D10: 1400 | E10: 14 | F10: 1800 | G10: 1500 | H10: 1900 | I10: Holding | K10: =D10/AVERAGEIFS($D$2:$D$73,$B$2:$B$73,B10,$A$2:$A$73,"<2023-1-1") -> 0.75675676 | N10: =(D10-C10)/C10 -> -0.034482759
A11: 44835 | B11: Electronics | C11: 1800 | D11: 1950 | E11: 15 | F11: 1900 | G11: 1900 | H11: 1850 | I11: Pre-Holiday | K11: =D11/AVERAGEIFS($D$2:$D$73,$B$2:$B$73,B11,$A$2:$A$73,"<2023-1-1") -> 1.0540541 | N11: =(D11-C11)/C11 -> 0.083333333
A12: 44866 | B12: Electronics | C12: 2800 | D12: 3100 | E12: 22 | F12: 1850 | G12: 3200 | H12: 1950 | I12: Black Friday | K12: =D12/AVERAGEIFS($D$2:$D$73,$B$2:$B$73,B12,$A$2:$A$73,"<2023-1-1") -> 1.6756757 | N12: =(D12-C12)/C12 -> 0.10714286
A13: 44896 | B13: Electronics | C13: 3500 | D13: 3400 | E13: 25 | F13: 1950 | G13: 3500 | H13: 2050 | I13: Holiday Peak | K13: =D13/AVERAGEIFS($D$2:$D$73,$B$2:$B$73,B13,$A$2:$A$73,"<2023-1-1") -> 1.8378378 | N13: =(D13-C13)/C13 -> -0.028571429
A14: 44927 | B14: Electronics | C14: 1300 | D14: 1200 | E14: 14 | F14: 2050 | G14: 1400 | H14: 2250 | I14: Inv Correction | K14: =D14/AVERAGEIFS($D$2:$D$73,$B$2:$B$73,B14,$A$2:$A$73,">=2023-01-01") -> 0.60377358 | N14: =(D14-C14)/C14 -> -0.076923077
A15: 44958 | B15: Electronics | C15: 1200 | D15: 1100 | E15: 14 | F15: 2250 | G15: 1250 | H15: 2400 | I15: Policy-based | K15: =D15/AVERAGEIFS($D$2:$D$73,$B$2:$B$73,B15,$A$2:$A$73,">=2023-1-1") -> 0.55345912 | N15: =(D15-C15)/C15 -> -0.083333333
A16: 44986 | B16: Electronics | C16: 1450 | D16: 1300 | E16: 15 | F16: 2400 | G16: 1500 | H16: 2600 | I16: Buffer Build | K16: =D16/AVERAGEIFS($D$2:$D$73,$B$2:$B$73,B16,$A$2:$A$73,">=2023-1-1") -> 0.65408805 | N16: =(D16-C16)/C16 -> -0.10344828
A17: 45017 | B17: Electronics | C17: 1350 | D17: 1450 | E17: 14 | F17: 2600 | G17: 1400 | H17: 2550 | I17: Minor Drift | K17: =D17/AVERAGEIFS($D$2:$D$73,$B$2:$B$73,B17,$A$2:$A$73,">=2023-1-1") -> 0.72955975 | N17: =(D17-C17)/C17 -> 0.074074074
A18: 45047 | B18: Electronics | C18: 1500 | D18: 1800 | E18: 16 | F18: 2550 | G18: 1600 | H18: 2350 | I18: Forecast Gap | K18: =D18/AVERAGEIFS($D$2:$D$73,$B$2:$B$73,B18,$A$2:$A$73,">=2023-1-1") -> 0.90566038 | N18: =(D18-C18)/C18 -> 0.2
A19: 45078 | B19: Electronics | C19: 1700 | D19: 2000 | E19: 14 | F19: 2350 | G19: 2500 | H19: 2850 | I19: Recovery | K19: =D19/AVERAGEIFS($D$2:$D$73,$B$2:$B$73,B19,$A$2:$A$73,">=2023-1-1") -> 1.0062893 | N19: =(D19-C19)/C19 -> 0.17647059
A20: 45108 | B20: Electronics | C20: 2000 | D20: 1900 | E20: 18 | F20: 2850 | G20: 2050 | H20: 3000 | I20: Policy-based | K20: =D20/AVERAGEIFS($D$2:$D$73,$B$2:$B$73,B20,$A$2:$A$73,">=2023-1-1") -> 0.95597484 | N20: =(D20-C20)/C20 -> -0.05
A21: 45139 | B21: Electronics | C21: 1600 | D21: 1500 | E21: 14 | F21: 3000 | G21: 1650 | H21: 3150 | I21: Cooling | K21: =D21/AVERAGEIFS($D$2:$D$73,$B$2:$B$73,B21,$A$2:$A$73,">=2023-1-1") -> 0.75471698 | N21: =(D21-C21)/C21 -> -0.0625
A22: 45170 | B22: Electronics | C22: 1550 | D22: 1500 | E22: 14 | F22: 3150 | G22: 1600 | H22: 3250 | I22: Quiet | K22: =D22/AVERAGEIFS($D$2:$D$73,$B$2:$B$73,B22,$A$2:$A$73,">=2023-1-1") -> 0.75471698 | N22: =(D22-C22)/C22 -> -0.032258065
A23: 45200 | B23: Electronics | C23: 1900 | D23: 2400 | E23: 15 | F23: 3250 | G23: 2500 | H23: 3350 | I23: Tech Launch | K23: =D23/AVERAGEIFS($D$2:$D$73,$B$2:$B$73,B23,$A$2:$A$73,">=2023-1-1") -> 1.2075472 | N23: =(D23-C23)/C23 -> 0.26315789
A24: 45231 | B24: Electronics | C24: 3000 | D24: 3800 | E24: 22 | F24: 3350 | G24: 4000 | H24: 3550 | I24: Peak Demand | K24: =D24/AVERAGEIFS($D$2:$D$73,$B$2:$B$73,B24,$A$2:$A$73,">=2023-1-1") -> 1.9119497 | N24: =(D24-C24)/C24 -> 0.26666667
A25: 45261 | B25: Electronics | C25: 3700 | D25: 3900 | E25: 25 | F25: 3550 | G25: 3800 | H25: 3450 | I25: Peak Fulfilled | K25: =D25/AVERAGEIFS($D$2:$D$73,$B$2:$B$73,B25,$A$2:$A$73,">=2023-1-1") -> 1.9622642 | N25: =(D25-C25)/C25 -> 0.054054054
A26: 44562 | B26: Basics | C26: 2000 | D26: 2100 | E26: 7 | F26: 1500 | G26: 2100 | H26: 1500 | I26: Forecast-match | K26: =D26/AVERAGEIFS($D$2:$D$73,$B$2:$B$73,B26,$A$2:$A$73,"<2023-1-1") -> 1.0456432 | N26: =(D26-C26)/C26 -> 0.05
A27: 44593 | B27: Basics | C27: 2100 | D27: 2050 | E27: 7 | F27: 1500 | G27: 2150 | H27: 1600 | I27: Stable | K27: =D27/AVERAGEIFS($D$2:$D$73,$B$2:$B$73,B27,$A$2:$A$73,"<2023-1-1") -> 1.0207469 | N27: =(D27-C27)/C27 -> -0.023809524
A28: 44621 | B28: Basics | C28: 1950 | D28: 2200 | E28: 8 | F28: 1600 | G28: 2000 | H28: 1400 | I28: Demand Surge | K28: =D28/AVERAGEIFS($D$2:$D$73,$B$2:$B$73,B28,$A$2:$A$73,"<2023-1-1") -> 1.0954357 | N28: =(D28-C28)/C28 -> 0.12820513
A29: 44652 | B29: Basics | C29: 2050 | D29: 2100 | E29: 7 | F29: 1400 | G29: 2100 | H29: 1400 | I29: Forecast-match | K29: =D29/AVERAGEIFS($D$2:$D$73,$B$2:$B$73,B29,$A$2:$A$73,"<2023-1-1") -> 1.0456432 | N29: =(D29-C29)/C29 -> 0.024390244
A30: 44682 | B30: Basics | C30: 2000 | D30: 2000 | E30: 7 | F30: 1400 | G30: 2050 | H30: 1450 | I30: Policy-based | K30: =D30/AVERAGEIFS($D$2:$D$73,$B$2:$B$73,B30,$A$2:$A$73,"<2023-1-1") -> 0.99585062 | N30: =(D30-C30)/C30 -> 0
A31: 44713 | B31: Basics | C31: 500 | D31: 1200 | E31: 25 | F31: 1450 | G31: 600 | H31: 850 | I31: Forecast Error | K31: =D31/AVERAGEIFS($D$2:$D$73,$B$2:$B$73,B31,$A$2:$A$73,"<2023-1-1") -> 0.59751037 | N31: =(D31-C31)/C31 -> 1.4
A32: 44743 | B32: Basics | C32: 2050 | D32: 2100 | E32: 7 | F32: 850 | G32: 2300 | H32: 1050 | I32: Chasing Demand | K32: =D32/AVERAGEIFS($D$2:$D$73,$B$2:$B$73,B32,$A$2:$A$73,"<2023-1-1") -> 1.0456432 | N32: =(D32-C32)/C32 -> 0.024390244
A33: 44774 | B33: Basics | C33: 2100 | D33: 2150 | E33: 7 | F33: 1050 | G33: 2150 | H33: 1050 | I33: Tight Inv | K33: =D33/AVERAGEIFS($D$2:$D$73,$B$2:$B$73,B33,$A$2:$A$73,"<2023-1-1") -> 1.0705394 | N33: =(D33-C33)/C33 -> 0.023809524
A34: 44805 | B34: Basics | C34: 1980 | D34: 1900 | E34: 7 | F34: 1050 | G34: 2000 | H34: 1150 | I34: Holding | K34: =D34/AVERAGEIFS($D$2:$D$73,$B$2:$B$73,B34,$A$2:$A$73,"<2023-1-1") -> 0.94605809 | N34: =(D34-C34)/C34 -> -0.04040404
A35: 44835 | B35: Basics | C35: 2020 | D35: 2050 | E35: 7 | F35: 1150 | G35: 2050 | H35: 1150 | I35: High Turnover | K35: =D35/AVERAGEIFS($D$2:$D$73,$B$2:$B$73,B35,$A$2:$A$73,"<2023-1-1") -> 1.0207469 | N35: =(D35-C35)/C35 -> 0.014851485
A36: 44866 | B36: Basics | C36: 2050 | D36: 2100 | E36: 7 | F36: 1150 | G36: 2100 | H36: 1150 | I36: Steady | K36: =D36/AVERAGEIFS($D$2:$D$73,$B$2:$B$73,B36,$A$2:$A$73,"<2023-1-1") -> 1.0456432 | N36: =(D36-C36)/C36 -> 0.024390244
A37: 44896 | B37: Basics | C37: 2100 | D37: 2150 | E37: 7 | F37: 1150 | G37: 2150 | H37: 1150 | I37: Year-End | K37: =D37/AVERAGEIFS($D$2:$D$73,$B$2:$B$73,B37,$A$2:$A$73,"<2023-1-1") -> 1.0705394 | N37: =(D37-C37)/C37 -> 0.023809524
A38: 44927 | B38: Basics | C38: 2000 | D38: 2100 | E38: 7 | F38: 1150 | G38: 2100 | H38: 1150 | I38: High Demand | K38: =D38/AVERAGEIFS($D$2:$D$73,$B$2:$B$73,B38,$A$2:$A$73,">=2023-1-1") -> 0.89361702 | N38: =(D38-C38)/C38 -> 0.05
A39: 44958 | B39: Basics | C39: 2150 | D39: 2200 | E39: 7 | F39: 1150 | G39: 2200 | H39: 1150 | I39: Steady Flow | K39: =D39/AVERAGEIFS($D$2:$D$73,$B$2:$B$73,B39,$A$2:$A$73,">=2023-1-1") -> 0.93617021 | N39: =(D39-C39)/C39 -> 0.023255814
A40: 44986 | B40: Basics | C40: 2000 | D40: 2500 | E40: 8 | F40: 1150 | G40: 2400 | H40: 1050 | I40: Surge | K40: =D40/AVERAGEIFS($D$2:$D$73,$B$2:$B$73,B40,$A$2:$A$73,">=2023-1-1") -> 1.0638298 | N40: =(D40-C40)/C40 -> 0.25
A41: 45017 | B41: Basics | C41: 2100 | D41: 2450 | E41: 7 | F41: 1050 | G41: 2500 | H41: 1100 | I41: High Sales | K41: =D41/AVERAGEIFS($D$2:$D$73,$B$2:$B$73,B41,$A$2:$A$73,">=2023-1-1") -> 1.0425532 | N41: =(D41-C41)/C41 -> 0.16666667
A42: 45047 | B42: Basics | C42: 2050 | D42: 2300 | E42: 7 | F42: 1100 | G42: 2400 | H42: 1200 | I42: High Sales | K42: =D42/AVERAGEIFS($D$2:$D$73,$B$2:$B$73,B42,$A$2:$A$73,">=2023-1-1") -> 0.9787234 | N42: =(D42-C42)/C42 -> 0.12195122
A43: 45078 | B43: Basics | C43: 550 | D43: 1200 | E43: 25 | F43: 1200 | G43: 1500 | H43: 1500 | I43: Large Error | K43: =D43/AVERAGEIFS($D$2:$D$73,$B$2:$B$73,B43,$A$2:$A$73,">=2023-1-1") -> 0.5106383 | N43: =(D43-C43)/C43 -> 1.1818182
A44: 45108 | B44: Basics | C44: 2100 | D44: 2400 | E44: 7 | F44: 1500 | G44: 2500 | H44: 1600 | I44: Refilling | K44: =D44/AVERAGEIFS($D$2:$D$73,$B$2:$B$73,B44,$A$2:$A$73,">=2023-1-1") -> 1.0212766 | N44: =(D44-C44)/C44 -> 0.14285714
A45: 45139 | B45: Basics | C45: 2150 | D45: 2600 | E45: 7 | F45: 1600 | G45: 2200 | H45: 1200 | I45: High Peak | K45: =D45/AVERAGEIFS($D$2:$D$73,$B$2:$B$73,B45,$A$2:$A$73,">=2023-1-1") -> 1.106383 | N45: =(D45-C45)/C45 -> 0.20930233
A46: 45170 | B46: Basics | C46: 2000 | D46: 2350 | E46: 7 | F46: 1200 | G46: 2400 | H46: 1250 | I46: Stable | K46: =D46/AVERAGEIFS($D$2:$D$73,$B$2:$B$73,B46,$A$2:$A$73,">=2023-1-1") -> 1 | N46: =(D46-C46)/C46 -> 0.175
A47: 45200 | B47: Basics | C47: 2050 | D47: 2500 | E47: 7 | F47: 1250 | G47: 2600 | H47: 1350 | I47: High Sales | K47: =D47/AVERAGEIFS($D$2:$D$73,$B$2:$B$73,B47,$A$2:$A$73,">=2023-1-1") -> 1.0638298 | N47: =(D47-C47)/C47 -> 0.2195122
A48: 45231 | B48: Basics | C48: 2100 | D48: 2700 | E48: 7 | F48: 1350 | G48: 2800 | H48: 1450 | I48: Holiday Demand | K48: =D48/AVERAGEIFS($D$2:$D$73,$B$2:$B$73,B48,$A$2:$A$73,">=2023-1-1") -> 1.1489362 | N48: =(D48-C48)/C48 -> 0.28571429
A49: 45261 | B49: Basics | C49: 2150 | D49: 2900 | E49: 7 | F49: 1450 | G49: 2900 | H49: 1450 | I49: Year-End | K49: =D49/AVERAGEIFS($D$2:$D$73,$B$2:$B$73,B49,$A$2:$A$73,">=2023-1-1") -> 1.2340426 | N49: =(D49-C49)/C49 -> 0.34883721
A50: 44562 | B50: Office | C50: 500 | D50: 450 | E50: 30 | F50: 800 | G50: 550 | H50: 900 | I50: Safety Stock | K50: =D50/AVERAGEIFS($D$2:$D$73,$B$2:$B$73,B50,$A$2:$A$73,"<2023-1-1") -> 0.7012987 | N50: =(D50-C50)/C50 -> -0.1
A51: 44593 | B51: Office | C51: 520 | D51: 500 | E51: 30 | F51: 900 | G51: 550 | H51: 950 | I51: Stable | K51: =D51/AVERAGEIFS($D$2:$D$73,$B$2:$B$73,B51,$A$2:$A$73,"<2023-1-1") -> 0.77922078 | N51: =(D51-C51)/C51 -> -0.038461538
A52: 44621 | B52: Office | C52: 510 | D52: 550 | E52: 30 | F52: 950 | G52: 550 | H52: 950 | I52: Policy-based | K52: =D52/AVERAGEIFS($D$2:$D$73,$B$2:$B$73,B52,$A$2:$A$73,"<2023-1-1") -> 0.85714286 | N52: =(D52-C52)/C52 -> 0.078431373
A53: 44652 | B53: Office | C53: 900 | D53: 850 | E53: 30 | F53: 950 | G53: 950 | H53: 1050 | I53: Spring Promo | K53: =D53/AVERAGEIFS($D$2:$D$73,$B$2:$B$73,B53,$A$2:$A$73,"<2023-1-1") -> 1.3246753 | N53: =(D53-C53)/C53 -> -0.055555556
A54: 44682 | B54: Office | C54: 530 | D54: 600 | E54: 30 | F54: 1050 | G54: 550 | H54: 1000 | I54: Promo Hangover | K54: =D54/AVERAGEIFS($D$2:$D$73,$B$2:$B$73,B54,$A$2:$A$73,"<2023-1-1") -> 0.93506494 | N54: =(D54-C54)/C54 -> 0.13207547
A55: 44713 | B55: Office | C55: 540 | D55: 550 | E55: 30 | F55: 1000 | G55: 550 | H55: 1000 | I55: Flat | K55: =D55/AVERAGEIFS($D$2:$D$73,$B$2:$B$73,B55,$A$2:$A$73,"<2023-1-1") -> 0.85714286 | N55: =(D55-C55)/C55 -> 0.018518519
A56: 44743 | B56: Office | C56: 550 | D56: 600 | E56: 30 | F56: 1000 | G56: 600 | H56: 1000 | I56: Steady | K56: =D56/AVERAGEIFS($D$2:$D$73,$B$2:$B$73,B56,$A$2:$A$73,"<2023-1-1") -> 0.93506494 | N56: =(D56-C56)/C56 -> 0.090909091
A57: 44774 | B57: Office | C57: 900 | D57: 850 | E57: 30 | F57: 1000 | G57: 900 | H57: 1050 | I57: Peak (School) | K57: =D57/AVERAGEIFS($D$2:$D$73,$B$2:$B$73,B57,$A$2:$A$73,"<2023-1-1") -> 1.3246753 | N57: =(D57-C57)/C57 -> -0.055555556
A58: 44805 | B58: Office | C58: 540 | D58: 500 | E58: 30 | F58: 1050 | G58: 500 | H58: 1050 | I58: Post-Peak | K58: =D58/AVERAGEIFS($D$2:$D$73,$B$2:$B$73,B58,$A$2:$A$73,"<2023-1-1") -> 0.77922078 | N58: =(D58-C58)/C58 -> -0.074074074
A59: 44835 | B59: Office | C59: 950 | D59: 1000 | E59: 30 | F59: 1050 | G59: 1000 | H59: 1050 | I59: Tax Year Spike | K59: =D59/AVERAGEIFS($D$2:$D$73,$B$2:$B$73,B59,$A$2:$A$73,"<2023-1-1") -> 1.5584416 | N59: =(D59-C59)/C59 -> 0.052631579
A60: 44866 | B60: Office | C60: 580 | D60: 600 | E60: 30 | F60: 1050 | G60: 600 | H60: 1050 | I60: Steady | K60: =D60/AVERAGEIFS($D$2:$D$73,$B$2:$B$73,B60,$A$2:$A$73,"<2023-1-1") -> 0.93506494 | N60: =(D60-C60)/C60 -> 0.034482759
A61: 44896 | B61: Office | C61: 590 | D61: 650 | E61: 30 | F61: 1050 | G61: 650 | H61: 1050 | I61: Steady | K61: =D61/AVERAGEIFS($D$2:$D$73,$B$2:$B$73,B61,$A$2:$A$73,"<2023-1-1") -> 1.012987 | N61: =(D61-C61)/C61 -> 0.10169492
A62: 44927 | B62: Office | C62: 520 | D62: 580 | E62: 30 | F62: 1050 | G62: 550 | H62: 1020 | I62: Post-Holiday | K62: =D62/AVERAGEIFS($D$2:$D$73,$B$2:$B$73,B62,$A$2:$A$73,">=2023-1-1") -> 0.66602871 | N62: =(D62-C62)/C62 -> 0.11538462
A63: 44958 | B63: Office | C63: 540 | D63: 620 | E63: 30 | F63: 1020 | G63: 550 | H63: 950 | I63: Stable | K63: =D63/AVERAGEIFS($D$2:$D$73,$B$2:$B$73,B63,$A$2:$A$73,">=2023-1-1") -> 0.71196172 | N63: =(D63-C63)/C63 -> 0.14814815
A64: 44986 | B64: Office | C64: 530 | D64: 600 | E64: 30 | F64: 950 | G64: 550 | H64: 900 | I64: Policy-based | K64: =D64/AVERAGEIFS($D$2:$D$73,$B$2:$B$73,B64,$A$2:$A$73,">=2023-1-1") -> 0.68899522 | N64: =(D64-C64)/C64 -> 0.13207547
A65: 45017 | B65: Office | C65: 920 | D65: 1200 | E65: 30 | F65: 900 | G65: 1200 | H65: 900 | I65: Spring Peak | K65: =D65/AVERAGEIFS($D$2:$D$73,$B$2:$B$73,B65,$A$2:$A$73,">=2023-1-1") -> 1.3779904 | N65: =(D65-C65)/C65 -> 0.30434783
A66: 45047 | B66: Office | C66: 550 | D66: 750 | E66: 30 | F66: 900 | G66: 700 | H66: 850 | I66: Promo Tail | K66: =D66/AVERAGEIFS($D$2:$D$73,$B$2:$B$73,B66,$A$2:$A$73,">=2023-1-1") -> 0.86124402 | N66: =(D66-C66)/C66 -> 0.36363636
A67: 45078 | B67: Office | C67: 560 | D67: 650 | E67: 30 | F67: 850 | G67: 700 | H67: 900 | I67: Stable | K67: =D67/AVERAGEIFS($D$2:$D$73,$B$2:$B$73,B67,$A$2:$A$73,">=2023-1-1") -> 0.74641148 | N67: =(D67-C67)/C67 -> 0.16071429
A68: 45108 | B68: Office | C68: 570 | D68: 800 | E68: 30 | F68: 900 | G68: 800 | H68: 900 | I68: Steady | K68: =D68/AVERAGEIFS($D$2:$D$73,$B$2:$B$73,B68,$A$2:$A$73,">=2023-1-1") -> 0.91866029 | N68: =(D68-C68)/C68 -> 0.40350877
A69: 45139 | B69: Office | C69: 580 | D69: 1500 | E69: 30 | F69: 900 | G69: 1500 | H69: 900 | I69: Back-to-Work | K69: =D69/AVERAGEIFS($D$2:$D$73,$B$2:$B$73,B69,$A$2:$A$73,">=2023-1-1") -> 1.722488 | N69: =(D69-C69)/C69 -> 1.5862069
A70: 45170 | B70: Office | C70: 560 | D70: 700 | E70: 30 | F70: 900 | G70: 700 | H70: 900 | I70: Stable | K70: =D70/AVERAGEIFS($D$2:$D$73,$B$2:$B$73,B70,$A$2:$A$73,">=2023-1-1") -> 0.80382775 | N70: =(D70-C70)/C70 -> 0.25
A71: 45200 | B71: Office | C71: 980 | D71: 1300 | E71: 30 | F71: 900 | G71: 1300 | H71: 900 | I71: Year-End Refresh | K71: =D71/AVERAGEIFS($D$2:$D$73,$B$2:$B$73,B71,$A$2:$A$73,">=2023-1-1") -> 1.492823 | N71: =(D71-C71)/C71 -> 0.32653061
A72: 45231 | B72: Office | C72: 600 | D72: 850 | E72: 30 | F72: 900 | G72: 850 | H72: 900 | I72: Holiday Gifting | K72: =D72/AVERAGEIFS($D$2:$D$73,$B$2:$B$73,B72,$A$2:$A$73,">=2023-1-1") -> 0.97607656 | N72: =(D72-C72)/C72 -> 0.41666667
A73: 45261 | B73: Office | C73: 610 | D73: 900 | E73: 30 | F73: 900 | G73: 900 | H73: 900 | I73: Year-End | K73: =D73/AVERAGEIFS($D$2:$D$73,$B$2:$B$73,B73,$A$2:$A$73,">=2023-1-1") -> 1.0334928 | N73: =(D73-C73)/C73 -> 0.47540984
A74: 45292 | B74: Electronics | F74: =data!J97 -> 0 | G74: =MAX(0,J74+I74-F74) -> 1440.5292 | H74: =F74+G74-I74 -> 1440.5292 | J74: =_xlfn.FORECAST.ETS(A74,$D$2:$D$25,$A$2:$A$25,12) -> 1440.5292 | L74: {=(AVERAGE(_xlfn._xlws.FILTER($K$2:$K$73, ($B$2:$B$73=B74) * (TEXT($A$2:$A$73, "mmm")=TEXT(A74, "mmm")))))} -> 0.6126976 | M74: =AVERAGEIFS($D$2:$D$109,$B$2:$B$109,B74,$A$2:$A$109,">=2023-1-1")*(1+$T$4)*L74 -> 1308.2439 | O74: =M74*(1+(1.96*$T$6)) -> 2061.6392 | P74: =M74*(1-(1.96*$T$6)) -> 554.84861 | Q74: =O74-P74 -> 1506.7906
A75: 45323 | B75: Electronics | F75: =H74 -> 1440.5292 | G75: =MAX(0,J75+I75-F75) -> 0 | H75: =F75+G75-I75 -> 1440.5292 | J75: =_xlfn.FORECAST.ETS(A75,$D$2:$D$25,$A$2:$A$25,12) -> 1341.6626 | L75: {=AVERAGE(_xlfn._xlws.FILTER($K$2:$K$73, ($B$2:$B$73=B75) * (TEXT($A$2:$A$73, "mmm")=TEXT(A75, "mmm"))))} -> 0.6145674 | M75: =AVERAGEIFS($D$2:$D$109,$B$2:$B$109,B75,$A$2:$A$109,">=2023-1-1")*(1+$T$4)*L75 -> 1312.2363 | O75: =M75*(1+(1.96*$T$6)) -> 2067.9308 | P75: =M75*(1-(1.96*$T$6)) -> 556.54186 | Q75: =O75-P75 -> 1511.389
A76: 45352 | B76: Electronics | F76: =H75 -> 1440.5292 | G76: =MAX(0,J76+I76-F76) -> 101.99146 | H76: =F76+G76-I76 -> 1542.5206 | J76: =_xlfn.FORECAST.ETS(A76,$D$2:$D$25,$A$2:$A$25,12) -> 1542.5206 | L76: {=AVERAGE(_xlfn._xlws.FILTER($K$2:$K$73, ($B$2:$B$73=B76) * (TEXT($A$2:$A$73, "mmm")=TEXT(A76, "mmm"))))} -> 0.7054224 | M76: =AVERAGEIFS($D$2:$D$109,$B$2:$B$109,B76,$A$2:$A$109,">=2023-1-1")*(1+$T$4)*L76 -> 1506.2317 | O76: =M76*(1+(1.96*$T$6)) -> 2373.6449 | P76: =M76*(1-(1.96*$T$6)) -> 638.81862 | Q76: =O76-P76 -> 1734.8262
A77: 45383 | B77: Electronics | F77: =H76 -> 1542.5206 | G77: =MAX(0,J77+I77-F77) -> 150.967 | H77: =F77+G77-I77 -> 1693.4876 | J77: =_xlfn.FORECAST.ETS(A77,$D$2:$D$25,$A$2:$A$25,12) -> 1693.4876 | L77: {=AVERAGE(_xlfn._xlws.FILTER($K$2:$K$73, ($B$2:$B$73=B77) * (TEXT($A$2:$A$73, "mmm")=TEXT(A77, "mmm"))))} -> 0.79721231 | M77: =AVERAGEIFS($D$2:$D$109,$B$2:$B$109,B77,$A$2:$A$109,">=2023-1-1")*(1+$T$4)*L77 -> 1702.2233 | O77: =M77*(1+(1.96*$T$6)) -> 2682.5047 | P77: =M77*(1-(1.96*$T$6)) -> 721.94201 | Q77: =O77-P77 -> 1960.5627
A78: 45413 | B78: Electronics | F78: =H77 -> 1693.4876 | G78: =MAX(0,J78+I78-F78) -> 350.86242 | H78: =F78+G78-I78 -> 2044.3501 | J78: =_xlfn.FORECAST.ETS(A78,$D$2:$D$25,$A$2:$A$25,12) -> 2044.3501 | L78: {=AVERAGE(_xlfn._xlws.FILTER($K$2:$K$73, ($B$2:$B$73=B78) * (TEXT($A$2:$A$73, "mmm")=TEXT(A78, "mmm"))))} -> 0.9663437 | M78: =AVERAGEIFS($D$2:$D$109,$B$2:$B$109,B78,$A$2:$A$109,">=2023-1-1")*(1+$T$4)*L78 -> 2063.356 | O78: =M78*(1+(1.96*$T$6)) -> 3251.6075 | P78: =M78*(1-(1.96*$T$6)) -> 875.10454 | Q78: =O78-P78 -> 2376.5029
A79: 45444 | B79: Electronics | F79: =H78 -> 2044.3501 | G79: =MAX(0,J79+I79-F79) -> 169.43369 | H79: =F79+G79-I79 -> 2213.7837 | J79: =_xlfn.FORECAST.ETS(A79,$D$2:$D$25,$A$2:$A$25,12) -> 2213.7837 | L79: {=AVERAGE(_xlfn._xlws.FILTER($K$2:$K$73, ($B$2:$B$73=B79) * (TEXT($A$2:$A$73, "mmm")=TEXT(A79, "mmm"))))} -> 0.98963114 | M79: =AVERAGEIFS($D$2:$D$109,$B$2:$B$109,B79,$A$2:$A$109,">=2023-1-1")*(1+$T$4)*L79 -> 2113.0798 | O79: =M79*(1+(1.96*$T$6)) -> 3329.9663 | P79: =M79*(1-(1.96*$T$6)) -> 896.19326 | Q79: =O79-P79 -> 2433.7731
A80: 45474 | B80: Electronics | F80: =H79 -> 2213.7837 | G80: =MAX(0,J80+I80-F80) -> 0 | H80: =F80+G80-I80 -> 2213.7837 | J80: =_xlfn.FORECAST.ETS(A80,$D$2:$D$25,$A$2:$A$25,12) -> 2187.9166 | L80: {=AVERAGE(_xlfn._xlws.FILTER($K$2:$K$73, ($B$2:$B$73=B80) * (TEXT($A$2:$A$73, "mmm")=TEXT(A80, "mmm"))))} -> 0.97798742 | M80: =AVERAGEIFS($D$2:$D$109,$B$2:$B$109,B80,$A$2:$A$109,">=2023-1-1")*(1+$T$4)*L80 -> 2088.2179 | O80: =M80*(1+(1.96*$T$6)) -> 3290.7869 | P80: =M80*(1-(1.96*$T$6)) -> 885.6489 | Q80: =O80-P80 -> 2405.138
A81: 45505 | B81: Electronics | F81: =H80 -> 2213.7837 | G81: =MAX(0,J81+I81-F81) -> 0 | H81: =F81+G81-I81 -> 2213.7837 | J81: =_xlfn.FORECAST.ETS(A81,$D$2:$D$25,$A$2:$A$25,12) -> 1757.8883 | L81: {=AVERAGE(_xlfn._xlws.FILTER($K$2:$K$73, ($B$2:$B$73=B81) * (TEXT($A$2:$A$73, "mmm")=TEXT(A81, "mmm"))))} -> 0.75573687 | M81: =AVERAGEIFS($D$2:$D$109,$B$2:$B$109,B81,$A$2:$A$109,">=2023-1-1")*(1+$T$4)*L81 -> 1613.6642 | O81: =M81*(1+(1.96*$T$6)) -> 2542.9458 | P81: =M81*(1-(1.96*$T$6)) -> 684.38255 | Q81: =O81-P81 -> 1858.5632
A82: 45536 | B82: Electronics | F82: =H81 -> 2213.7837 | G82: =MAX(0,J82+I82-F82) -> 0 | H82: =F82+G82-I82 -> 2213.7837 | J82: =_xlfn.FORECAST.ETS(A82,$D$2:$D$25,$A$2:$A$25,12) -> 1753.8958 | L82: {=AVERAGE(_xlfn._xlws.FILTER($K$2:$K$73, ($B$2:$B$73=B82) * (TEXT($A$2:$A$73, "mmm")=TEXT(A82, "mmm"))))} -> 0.75573687 | M82: =AVERAGEIFS($D$2:$D$109,$B$2:$B$109,B82,$A$2:$A$109,">=2023-1-1")*(1+$T$4)*L82 -> 1613.6642 | O82: =M82*(1+(1.96*$T$6)) -> 2542.9458 | P82: =M82*(1-(1.96*$T$6)) -> 684.38255 | Q82: =O82-P82 -> 1858.5632
A83: 45566 | B83: Electronics | F83: =H82 -> 2213.7837 | G83: =MAX(0,J83+I83-F83) -> 260.07718 | H83: =F83+G83-I83 -> 2473.8609 | J83: =_xlfn.FORECAST.ETS(A83,$D$2:$D$25,$A$2:$A$25,12) -> 2473.8609 | L83: {=AVERAGE(_xlfn._xlws.FILTER($K$2:$K$73, ($B$2:$B$73=B83) * (TEXT($A$2:$A$73, "mmm")=TEXT(A83, "mmm"))))} -> 1.1308006 | M83: =AVERAGEIFS($D$2:$D$109,$B$2:$B$109,B83,$A$2:$A$109,">=2023-1-1")*(1+$T$4)*L83 -> 2414.5076 | O83: =M83*(1+(1.96*$T$6)) -> 3804.9813 | P83: =M83*(1-(1.96*$T$6)) -> 1024.0339 | Q83: =O83-P83 -> 2780.9474
A84: 45597 | B84: Electronics | F84: =H83 -> 2473.8609 | G84: =MAX(0,J84+I84-F84) -> 1271.0017 | H84: =F84+G84-I84 -> 3744.8626 | J84: =_xlfn.FORECAST.ETS(A84,$D$2:$D$25,$A$2:$A$25,12) -> 3744.8626 | L84: {=AVERAGE(_xlfn._xlws.FILTER($K$2:$K$73, ($B$2:$B$73=B84) * (TEXT($A$2:$A$73, "mmm")=TEXT(A84, "mmm"))))} -> 1.7938127 | M84: =AVERAGEIFS($D$2:$D$109,$B$2:$B$109,B84,$A$2:$A$109,">=2023-1-1")*(1+$T$4)*L84 -> 3830.184 | O84: =M84*(1+(1.96*$T$6)) -> 6035.9215 | P84: =M84*(1-(1.96*$T$6)) -> 1624.4465 | Q84: =O84-P84 -> 4411.475
A85: 45627 | B85: Electronics | F85: =H84 -> 3744.8626 | G85: =MAX(0,J85+I85-F85) -> 43.700066 | H85: =F85+G85-I85 -> 3788.5627 | J85: =_xlfn.FORECAST.ETS(A85,$D$2:$D$25,$A$2:$A$25,12) -> 3788.5627 | L85: {=AVERAGE(_xlfn._xlws.FILTER($K$2:$K$73, ($B$2:$B$73=B85) * (TEXT($A$2:$A$73, "mmm")=TEXT(A85, "mmm"))))} -> 1.900051 | M85: =AVERAGEIFS($D$2:$D$109,$B$2:$B$109,B85,$A$2:$A$109,">=2023-1-1")*(1+$T$4)*L85 -> 4057.0261 | O85: =M85*(1+(1.96*$T$6)) -> 6393.3981 | P85: =M85*(1-(1.96*$T$6)) -> 1720.6541 | Q85: =O85-P85 -> 4672.744
A86: 45292 | B86: Basics | F86: =data!J121 -> 0 | G86: =MAX(0,J86+I86-F86) -> 2938.0356 | H86: =F86+G86-I86 -> 2938.0356 | J86: =_xlfn.FORECAST.ETS(A86,$D$26:$D$49,$A$26:$A$49,12) -> 2938.0356 | L86: {=AVERAGE(_xlfn._xlws.FILTER($K$2:$K$73, ($B$2:$B$73=B86) * (TEXT($A$2:$A$73, "mmm")=TEXT(A86, "mmm"))))} -> 0.96963009 | M86: =AVERAGEIFS($D$2:$D$109,$B$2:$B$109,B86,$A$2:$A$109,">=2023-1-1")*(1+$U$4)*L86 -> 2666.2816 | O86: =M86*(1+(1.96*$T$6)) -> 4201.7476 | P86: =M86*(1-(1.96*$T$6)) -> 1130.8156 | Q86: =O86-P86 -> 3070.932
A87: 45323 | B87: Basics | F87: =H86 -> 2938.0356 | G87: =MAX(0,J87+I87-F87) -> 188.51255 | H87: =F87+G87-I87 -> 3126.5481 | J87: =_xlfn.FORECAST.ETS(A87,$D$26:$D$49,$A$26:$A$49,12) -> 3126.5481 | L87: {=AVERAGE(_xlfn._xlws.FILTER($K$2:$K$73, ($B$2:$B$73=B87) * (TEXT($A$2:$A$73, "mmm")=TEXT(A87, "mmm"))))} -> 0.97845855 | M87: =AVERAGEIFS($D$2:$D$109,$B$2:$B$109,B87,$A$2:$A$109,">=2023-1-1")*(1+$U$4)*L87 -> 2690.558 | O87: =M87*(1+(1.96*$T$6)) -> 4240.0044 | P87: =M87*(1-(1.96*$T$6)) -> 1141.1116 | Q87: =O87-P87 -> 3098.8928
A88: 45352 | B88: Basics | F88: =H87 -> 3126.5481 | G88: =MAX(0,J88+I88-F88) -> 388.7003 | H88: =F88+G88-I88 -> 3515.2484 | J88: =_xlfn.FORECAST.ETS(A88,$D$26:$D$49,$A$26:$A$49,12) -> 3515.2484 | L88: {=AVERAGE(_xlfn._xlws.FILTER($K$2:$K$73, ($B$2:$B$73=B88) * (TEXT($A$2:$A$73, "mmm")=TEXT(A88, "mmm"))))} -> 1.0796327 | M88: =AVERAGEIFS($D$2:$D$109,$B$2:$B$109,B88,$A$2:$A$109,">=2023-1-1")*(1+$U$4)*L88 -> 2968.766 | O88: =M88*(1+(1.96*$T$6)) -> 4678.4277 | P88: =M88*(1-(1.96*$T$6)) -> 1259.1044 | Q88: =O88-P88 -> 3419.3232
A89: 45383 | B89: Basics | F89: =H88 -> 3515.2484 | G89: =MAX(0,J89+I89-F89) -> 38.791454 | H89: =F89+G89-I89 -> 3554.0399 | J89: =_xlfn.FORECAST.ETS(A89,$D$26:$D$49,$A$26:$A$49,12) -> 3554.0399 | L89: {=AVERAGE(_xlfn._xlws.FILTER($K$2:$K$73, ($B$2:$B$73=B89) * (TEXT($A$2:$A$73, "mmm")=TEXT(A89, "mmm"))))} -> 1.0440982 | M89: =AVERAGEIFS($D$2:$D$109,$B$2:$B$109,B89,$A$2:$A$109,">=2023-1-1")*(1+$U$4)*L89 -> 2871.0534 | O89: =M89*(1+(1.96*$T$6)) -> 4524.4439 | P89: =M89*(1-(1.96*$T$6)) -> 1217.6628 | Q89: =O89-P89 -> 3306.7811
A90: 45413 | B90: Basics | F90: =H89 -> 3554.0399 | G90: =MAX(0,J90+I90-F90) -> 0 | H90: =F90+G90-I90 -> 3554.0399 | J90: =_xlfn.FORECAST.ETS(A90,$D$26:$D$49,$A$26:$A$49,12) -> 3492.7996 | L90: {=AVERAGE(_xlfn._xlws.FILTER($K$2:$K$73, ($B$2:$B$73=B90) * (TEXT($A$2:$A$73, "mmm")=TEXT(A90, "mmm"))))} -> 0.98728701 | M90: =AVERAGEIFS($D$2:$D$109,$B$2:$B$109,B90,$A$2:$A$109,">=2023-1-1")*(1+$U$4)*L90 -> 2714.8345 | O90: =M90*(1+(1.96*$T$6)) -> 4278.2612 | P90: =M90*(1-(1.96*$T$6)) -> 1151.4077 | Q90: =O90-P90 -> 3126.8535
A91: 45444 | B91: Basics | F91: =H90 -> 3554.0399 | G91: =MAX(0,J91+I91-F91) -> 0 | H91: =F91+G91-I91 -> 3554.0399 | J91: =_xlfn.FORECAST.ETS(A91,$D$26:$D$49,$A$26:$A$49,12) -> 2652.1769 | L91: {=AVERAGE(_xlfn._xlws.FILTER($K$2:$K$73, ($B$2:$B$73=B91) * (TEXT($A$2:$A$73, "mmm")=TEXT(A91, "mmm"))))} -> 0.55407434 | M91: =AVERAGEIFS($D$2:$D$109,$B$2:$B$109,B91,$A$2:$A$109,">=2023-1-1")*(1+$U$4)*L91 -> 1523.5895 | O91: =M91*(1+(1.96*$T$6)) -> 2400.9986 | P91: =M91*(1-(1.96*$T$6)) -> 646.18033 | Q91: =O91-P91 -> 1754.8183
A92: 45474 | B92: Basics | F92: =H91 -> 3554.0399 | G92: =MAX(0,J92+I92-F92) -> 229.7399 | H92: =F92+G92-I92 -> 3783.7798 | J92: =_xlfn.FORECAST.ETS(A92,$D$26:$D$49,$A$26:$A$49,12) -> 3783.7798 | L92: {=AVERAGE(_xlfn._xlws.FILTER($K$2:$K$73, ($B$2:$B$73=B92) * (TEXT($A$2:$A$73, "mmm")=TEXT(A92, "mmm"))))} -> 1.0334599 | M92: =AVERAGEIFS($D$2:$D$109,$B$2:$B$109,B92,$A$2:$A$109,">=2023-1-1")*(1+$U$4)*L92 -> 2841.8002 | O92: =M92*(1+(1.96*$T$6)) -> 4478.3444 | P92: =M92*(1-(1.96*$T$6)) -> 1205.256 | Q92: =O92-P92 -> 3273.0884
A93: 45505 | B93: Basics | F93: =H92 -> 3783.7798 | G93: =MAX(0,J93+I93-F93) -> 209.65087 | H93: =F93+G93-I93 -> 3993.4307 | J93: =_xlfn.FORECAST.ETS(A93,$D$26:$D$49,$A$26:$A$49,12) -> 3993.4307 | L93: {=AVERAGE(_xlfn._xlws.FILTER($K$2:$K$73, ($B$2:$B$73=B93) * (TEXT($A$2:$A$73, "mmm")=TEXT(A93, "mmm"))))} -> 1.0884612 | M93: =AVERAGEIFS($D$2:$D$109,$B$2:$B$109,B93,$A$2:$A$109,">=2023-1-1")*(1+$U$4)*L93 -> 2993.0425 | O93: =M93*(1+(1.96*$T$6)) -> 4716.6845 | P93: =M93*(1-(1.96*$T$6)) -> 1269.4005 | Q93: =O93-P93 -> 3447.284
A94: 45536 | B94: Basics | F94: =H93 -> 3993.4307 | G94: =MAX(0,J94+I94-F94) -> 0 | H94: =F94+G94-I94 -> 3993.4307 | J94: =_xlfn.FORECAST.ETS(A94,$D$26:$D$49,$A$26:$A$49,12) -> 3831.2115 | L94: {=AVERAGE(_xlfn._xlws.FILTER($K$2:$K$73, ($B$2:$B$73=B94) * (TEXT($A$2:$A$73, "mmm")=TEXT(A94, "mmm"))))} -> 0.97302905 | M94: =AVERAGEIFS($D$2:$D$109,$B$2:$B$109,B94,$A$2:$A$109,">=2023-1-1")*(1+$U$4)*L94 -> 2675.628 | O94: =M94*(1+(1.96*$T$6)) -> 4216.4764 | P94: =M94*(1-(1.96*$T$6)) -> 1134.7796 | Q94: =O94-P94 -> 3081.6969
A95: 45566 | B95: Basics | F95: =H94 -> 3993.4307 | G95: =MAX(0,J95+I95-F95) -> 76.611136 | H95: =F95+G95-I95 -> 4070.0418 | J95: =_xlfn.FORECAST.ETS(A95,$D$26:$D$49,$A$26:$A$49,12) -> 4070.0418 | L95: {=AVERAGE(_xlfn._xlws.FILTER($K$2:$K$73, ($B$2:$B$73=B95) * (TEXT($A$2:$A$73, "mmm")=TEXT(A95, "mmm"))))} -> 1.0422883 | M95: =AVERAGEIFS($D$2:$D$109,$B$2:$B$109,B95,$A$2:$A$109,">=2023-1-1")*(1+$U$4)*L95 -> 2866.0767 | O95: =M95*(1+(1.96*$T$6)) -> 4516.6013 | P95: =M95*(1-(1.96*$T$6)) -> 1215.5521 | Q95: =O95-P95 -> 3301.0492
A96: 45597 | B96: Basics | F96: =H95 -> 4070.0418 | G96: =MAX(0,J96+I96-F96) -> 212.7943 | H96: =F96+G96-I96 -> 4282.8361 | J96: =_xlfn.FORECAST.ETS(A96,$D$26:$D$49,$A$26:$A$49,12) -> 4282.8361 | L96: {=AVERAGE(_xlfn._xlws.FILTER($K$2:$K$73, ($B$2:$B$73=B96) * (TEXT($A$2:$A$73, "mmm")=TEXT(A96, "mmm"))))} -> 1.0972897 | M96: =AVERAGEIFS($D$2:$D$109,$B$2:$B$109,B96,$A$2:$A$109,">=2023-1-1")*(1+$U$4)*L96 -> 3017.3189 | O96: =M96*(1+(1.96*$T$6)) -> 4754.9413 | P96: =M96*(1-(1.96*$T$6)) -> 1279.6965 | Q96: =O96-P96 -> 3475.2448
A97: 45627 | B97: Basics | F97: =H96 -> 4282.8361 | G97: =MAX(0,J97+I97-F97) -> 22.548248 | H97: =F97+G97-I97 -> 4305.3844 | J97: =_xlfn.FORECAST.ETS(A97,$D$26:$D$49,$A$26:$A$49,12) -> 4305.3844 | L97: {=AVERAGE(_xlfn._xlws.FILTER($K$2:$K$73, ($B$2:$B$73=B97) * (TEXT($A$2:$A$73, "mmm")=TEXT(A97, "mmm"))))} -> 1.152291 | M97: =AVERAGEIFS($D$2:$D$109,$B$2:$B$109,B97,$A$2:$A$109,">=2023-1-1")*(1+$U$4)*L97 -> 3168.5611 | O97: =M97*(1+(1.96*$T$6)) -> 4993.2814 | P97: =M97*(1-(1.96*$T$6)) -> 1343.8409 | Q97: =O97-P97 -> 3649.4404
A98: 45292 | B98: Office | F98: =data!J145 -> 0 | G98: =MAX(0,J98+I98-F98) -> 830.46246 | H98: =F98+G98-I98 -> 830.46246 | J98: =_xlfn.FORECAST.ETS(A98,$D$50:$D$73,$A$50:$A$73,12) -> 830.46246 | L98: {=AVERAGE(_xlfn._xlws.FILTER($K$2:$K$73, ($B$2:$B$73=B98) * (TEXT($A$2:$A$73, "mmm")=TEXT(A98, "mmm"))))} -> 0.6836637 | M98: =AVERAGEIFS($D$2:$D$109,$B$2:$B$109,B98,$A$2:$A$109,">=2023-1-1")*(1+$V$4)*L98 -> 807.98469 | O98: =M98*(1+(1.96*$T$6)) -> 1273.2893 | P98: =M98*(1-(1.96*$T$6)) -> 342.68012 | Q98: =O98-P98 -> 930.60915
A99: 45323 | B99: Office | F99: =H98 -> 830.46246 | G99: =MAX(0,J99+I99-F99) -> 39.764446 | H99: =F99+G99-I99 -> 870.2269 | J99: =_xlfn.FORECAST.ETS(A99,$D$50:$D$73,$A$50:$A$73,12) -> 870.2269 | L99: {=AVERAGE(_xlfn._xlws.FILTER($K$2:$K$73, ($B$2:$B$73=B99) * (TEXT($A$2:$A$73, "mmm")=TEXT(A99, "mmm"))))} -> 0.74559125 | M99: =AVERAGEIFS($D$2:$D$109,$B$2:$B$109,B99,$A$2:$A$109,">=2023-1-1")*(1+$V$4)*L99 -> 881.17347 | O99: =M99*(1+(1.96*$T$6)) -> 1388.6262 | P99: =M99*(1-(1.96*$T$6)) -> 373.72073 | Q99: =O99-P99 -> 1014.9055
A100: 45352 | B100: Office | F100: =H99 -> 870.2269 | G100: =MAX(0,J100+I100-F100) -> 0 | H100: =F100+G100-I100 -> 870.2269 | J100: =_xlfn.FORECAST.ETS(A100,$D$50:$D$73,$A$50:$A$73,12) -> 850.04973 | L100: {=AVERAGE(_xlfn._xlws.FILTER($K$2:$K$73, ($B$2:$B$73=B100) * (TEXT($A$2:$A$73, "mmm")=TEXT(A100, "mmm"))))} -> 0.77306904 | M100: =AVERAGEIFS($D$2:$D$109,$B$2:$B$109,B100,$A$2:$A$109,">=2023-1-1")*(1+$V$4)*L100 -> 913.64796 | O100: =M100*(1+(1.96*$T$6)) -> 1439.8022 | P100: =M100*(1-(1.96*$T$6)) -> 387.49371 | Q100: =O100-P100 -> 1052.3085
...

Sheet data
A1: Date | B1: Category | C1: Forecast | D1: Actual | E1: Lead Time | F1: Start Inv | G1: Production | H1: End Inv | I1: Logic/Driver
A2: 44562 | B2: Electronics | C2: 1200 | D2: 1150 | E2: 14 | F2: 2000 | G2: 1250 | H2: 2100 | I2: Policy-based
A3: 44593 | B3: Electronics | C3: 1150 | D3: 1250 | E3: 14 | F3: 2100 | G3: 1200 | H3: 2050 | I3: Policy-based
A4: 44621 | B4: Electronics | C4: 1300 | D4: 1400 | E4: 15 | F4: 2050 | G4: 1350 | H4: 2000 | I4: Buffer Build
A5: 44652 | B5: Electronics | C5: 1250 | D5: 1600 | E5: 14 | F5: 2000 | G5: 1300 | H5: 1700 | I5: Supply Lag
A6: 44682 | B6: Electronics | C6: 1400 | D6: 1900 | E6: 16 | F6: 1700 | G6: 1450 | H6: 1250 | I6: High Sales
A7: 44713 | B7: Electronics | C7: 1600 | D7: 1800 | E7: 14 | F7: 1250 | G7: 2100 | H7: 1550 | I7: Recovery
A8: 44743 | B8: Electronics | C8: 1900 | D8: 1850 | E8: 18 | F8: 1550 | G8: 1950 | H8: 1650 | I8: Refilling
A9: 44774 | B9: Electronics | C9: 1500 | D9: 1400 | E9: 14 | F9: 1650 | G9: 1550 | H9: 1800 | I9: Stabilizing
A10: 44805 | B10: Electronics | C10: 1450 | D10: 1400 | E10: 14 | F10: 1800 | G10: 1500 | H10: 1900 | I10: Holding
A11: 44835 | B11: Electronics | C11: 1800 | D11: 1950 | E11: 15 | F11: 1900 | G11: 1900 | H11: 1850 | I11: Pre-Holiday
A12: 44866 | B12: Electronics | C12: 2800 | D12: 3100 | E12: 22 | F12: 1850 | G12: 3200 | H12: 1950 | I12: Black Friday
A13: 44896 | B13: Electronics | C13: 3500 | D13: 3400 | E13: 25 | F13: 1950 | G13: 3500 | H13: 2050 | I13: Holiday Peak
... A73: 45261 | B73: Office | C73: 610 | D73: 900 | E73: 30 | F73: 900 | G73: 900 | H73: 900 | I73: Year-End
